Instruction Memory/IM_with_pc.v
//Siddharth Singh and Chaitany Pandiya
//17CO146 and 17CO112
//register using Verilog
//1 January 2019
module IM_with_pc(output reg[31:0] q,input clock,reset);
parameter addr_width=4,ins_width=8;
  reg [addr_width-1:0] pc;
  reg [ins_width-1:0] ins_memory[2**addr_width-1:0];
  initial
    begin
      pc=0;
      ins_memory[0]=8'b00000000;
      ins_memory[1]=8'b00000001;
      ins_memory[2]=8'b00000010;
      ins_memory[3]=8'b00000011;
      ins_memory[4]=8'b00000100;
      ins_memory[5]=8'b00000101;
      ins_memory[6]=8'b00000110;
      ins_memory[7]=8'b00000111;
      ins_memory[8]=8'b00001000;
      ins_memory[9]=8'b00001001;
      ins_memory[10]=8'b00001010;
      ins_memory[11]=8'b00001011;
      ins_memory[12]=8'b00001100;
      ins_memory[13]=8'b00001101;
      ins_memory[14]=8'b00001110;
      ins_memory[15]=8'b00001111;
    end
  always @(posedge clock)
    begin
      //$display("Instruction in IM %d",ins_memory[pc]);
      pc=pc+4;
      if(reset)
      begin
        pc=0;
      end
      q[7:0]=ins_memory[pc];
      q[15:8]=ins_memory[pc+1];
      q[23:16]=ins_memory[pc+2];
      q[31:24]=ins_memory[pc+3];
    end
endmodule

Instruction Memory/IM_with_pc_tb.v
//Siddharth Singh and Chaitany Pandiya
//17CO146 and 17CO112
//register using Verilog
//1 January 2019
`timescale 1ns/100ps
`include "IM_with_pc.v"
module test_IM;
initial
begin
    $dumpfile("IM_with_pc.vcd");
    $dumpvars(0,test_IM);
end
  wire [31:0] IMout;
  reg clock=1,reset=0;
  IM_with_pc IM(IMout,clock,reset);
  always
  begin
    #20 clock=~clock;
  end
  always
  begin
  #160 reset=~reset;
  end
initial
begin
#2000 $finish;
end
endmodule

Instruction Memory/IM_with_pc.vcd
$date
	Thu Jan  3 17:33:04 2019
$end
$version
	Icarus Verilog
$end
$timescale
	100ps
$end
$scope module test_IM $end
$var wire 32 ! IMout [31:0] $end
$var reg 1 " clock $end
$var reg 1 # reset $end
$scope module IM $end
$var wire 1 " clock $end
$var wire 1 # reset $end
$var reg 4 $ pc [3:0] $end
$var reg 32 % q [31:0] $end
$upscope $end
$upscope $end
$enddefinitions $end
#0
$dumpvars
b111000001100000010100000100 %
b100 $
0#
1"
b111000001100000010100000100 !
$end
#200
0"
#400
b1011000010100000100100001000 !
b1011000010100000100100001000 %
b1000 $
1"
#600
0"
#800
b1111000011100000110100001100 !
b1111000011100000110100001100 %
b1100 $
1"
#1000
0"
#1200
b11000000100000000100000000 !
b11000000100000000100000000 %
b0 $
1"
#1400
0"
#1600
b0 $
1"
1#
#1800
0"
#2000
b0 $
1"
#2200
0"
#2400
b0 $
1"
#2600
0"
#2800
b0 $
1"
#3000
0"
#3200
b111000001100000010100000100 !
b111000001100000010100000100 %
b100 $
1"
0#
#3400
0"
#3600
b1011000010100000100100001000 !
b1011000010100000100100001000 %
b1000 $
1"
#3800
0"
#4000
b1111000011100000110100001100 !
b1111000011100000110100001100 %
b1100 $
1"
#4200
0"
#4400
b11000000100000000100000000 !
b11000000100000000100000000 %
b0 $
1"
#4600
0"
#4800
b0 $
1"
1#
#5000
0"
#5200
b0 $
1"
#5400
0"
#5600
b0 $
1"
#5800
0"
#6000
b0 $
1"
#6200
0"
#6400
b111000001100000010100000100 !
b111000001100000010100000100 %
b100 $
1"
0#
#6600
0"
#6800
b1011000010100000100100001000 !
b1011000010100000100100001000 %
b1000 $
1"
#7000
0"
#7200
b1111000011100000110100001100 !
b1111000011100000110100001100 %
b1100 $
1"
#7400
0"
#7600
b11000000100000000100000000 !
b11000000100000000100000000 %
b0 $
1"
#7800
0"
#8000
b0 $
1"
1#
#8200
0"
#8400
b0 $
1"
#8600
0"
#8800
b0 $
1"
#9000
0"
#9200
b0 $
1"
#9400
0"
#9600
b111000001100000010100000100 !
b111000001100000010100000100 %
b100 $
1"
0#
#9800
0"
#10000
b1011000010100000100100001000 !
b1011000010100000100100001000 %
b1000 $
1"
#10200
0"
#10400
b1111000011100000110100001100 !
b1111000011100000110100001100 %
b1100 $
1"
#10600
0"
#10800
b11000000100000000100000000 !
b11000000100000000100000000 %
b0 $
1"
#11000
0"
#11200
b0 $
1"
1#
#11400
0"
#11600
b0 $
1"
#11800
0"
#12000
b0 $
1"
#12200
0"
#12400
b0 $
1"
#12600
0"
#12800
b111000001100000010100000100 !
b111000001100000010100000100 %
b100 $
1"
0#
#13000
0"
#13200
b1011000010100000100100001000 !
b1011000010100000100100001000 %
b1000 $
1"
#13400
0"
#13600
b1111000011100000110100001100 !
b1111000011100000110100001100 %
b1100 $
1"
#13800
0"
#14000
b11000000100000000100000000 !
b11000000100000000100000000 %
b0 $
1"
#14200
0"
#14400
b0 $
1"
1#
#14600
0"
#14800
b0 $
1"
#15000
0"
#15200
b0 $
1"
#15400
0"
#15600
b0 $
1"
#15800
0"
#16000
b111000001100000010100000100 !
b111000001100000010100000100 %
b100 $
1"
0#
#16200
0"
#16400
b1011000010100000100100001000 !
b1011000010100000100100001000 %
b1000 $
1"
#16600
0"
#16800
b1111000011100000110100001100 !
b1111000011100000110100001100 %
b1100 $
1"
#17000
0"
#17200
b11000000100000000100000000 !
b11000000100000000100000000 %
b0 $
1"
#17400
0"
#17600
b0 $
1"
1#
#17800
0"
#18000
b0 $
1"
#18200
0"
#18400
b0 $
1"
#18600
0"
#18800
b0 $
1"
#19000
0"
#19200
b111000001100000010100000100 !
b111000001100000010100000100 %
b100 $
1"
0#
#19400
0"
#19600
b1011000010100000100100001000 !
b1011000010100000100100001000 %
b1000 $
1"
#19800
0"
#20000
b1111000011100000110100001100 !
b1111000011100000110100001100 %
b1100 $
1"
